m3ba/__init__.py
m3ba/m3ba.py
m3ba-0.0.1.dist-info/METADATA
m3ba-0.0.1.dist-info/WHEEL
m3ba-0.0.1.dist-info/top_level.txt
m3ba-0.0.1.dist-info/RECORD
