Metadata-Version: 2.1
Name: m3ba
Version: 0.0.1
Summary: Python Functionalities to Analyse MD data by the M3B lab
Author: M3B
Author-email: help@m3b.com
License: UNKNOWN
Platform: UNKNOWN
